sml2mqtt/__args__.py
sml2mqtt/__init__.py
sml2mqtt/__log__.py
sml2mqtt/__main__.py
sml2mqtt/__version__.py
sml2mqtt/errors.py
sml2mqtt/config/__init__.py
sml2mqtt/config/config.py
sml2mqtt/config/device.py
sml2mqtt/config/inputs.py
sml2mqtt/config/logging.py
sml2mqtt/config/mqtt.py
sml2mqtt/config/mqtt_tls.py
sml2mqtt/config/operations.py
sml2mqtt/config/types.py
sml2mqtt/const/__init__.py
sml2mqtt/const/date_time_finder.py
sml2mqtt/const/protocols.py
sml2mqtt/const/sml_helpers.py
sml2mqtt/const/task.py
sml2mqtt/const/time_series.py
sml2mqtt/mqtt/__init__.py
sml2mqtt/mqtt/connect_delay.py
sml2mqtt/mqtt/errors.py
sml2mqtt/mqtt/mqtt.py
sml2mqtt/mqtt/mqtt_obj.py
sml2mqtt/runtime/__init__.py
sml2mqtt/runtime/shutdown.py
sml2mqtt/sml_device/__init__.py
sml2mqtt/sml_device/device_status.py
sml2mqtt/sml_device/setup_device.py
sml2mqtt/sml_device/sml_device.py
sml2mqtt/sml_device/sml_devices.py
sml2mqtt/sml_device/stream_reader_group.py
sml2mqtt/sml_device/watchdog.py
sml2mqtt/sml_source/__init__.py
sml2mqtt/sml_source/http.py
sml2mqtt/sml_source/serial.py
sml2mqtt/sml_source/setup_source.py
sml2mqtt/sml_value/__init__.py
sml2mqtt/sml_value/base.py
sml2mqtt/sml_value/setup_operations.py
sml2mqtt/sml_value/sml_value.py
sml2mqtt/sml_value/sml_values.py
sml2mqtt/sml_value/operations/__init__.py
sml2mqtt/sml_value/operations/_helper.py
sml2mqtt/sml_value/operations/actions.py
sml2mqtt/sml_value/operations/date_time.py
sml2mqtt/sml_value/operations/filter.py
sml2mqtt/sml_value/operations/math.py
sml2mqtt/sml_value/operations/operations.py
sml2mqtt/sml_value/operations/time_series.py
sml2mqtt/sml_value/operations/workarounds.py
sml2mqtt-3.5.2.dist-info/licenses/LICENSE
sml2mqtt-3.5.2.dist-info/METADATA
sml2mqtt-3.5.2.dist-info/WHEEL
sml2mqtt-3.5.2.dist-info/entry_points.txt
sml2mqtt-3.5.2.dist-info/top_level.txt
sml2mqtt-3.5.2.dist-info/RECORD
