Metadata-Version: 2.4
Name: sml2mqtt
Version: 3.5.2
Summary: A sml (Smart Message Language) energy meter to MQTT bridge. Can read from serial ports or http (e.g. Tibber Pulse).
Home-page: https://github.com/spacemanspiff2007/sml2mqtt
Author: spaceman_spiff
Project-URL: GitHub, https://github.com/spacemanspiff2007/sml2mqtt
Keywords: mqtt,sml,Smart Message Language,energy meter,tibber
Classifier: Development Status :: 4 - Beta
Classifier: Framework :: AsyncIO
Classifier: License :: OSI Approved :: GNU General Public License v3 or later (GPLv3+)
Classifier: Operating System :: OS Independent
Classifier: Programming Language :: Python :: 3.10
Classifier: Programming Language :: Python :: 3.11
Classifier: Programming Language :: Python :: 3.12
Classifier: Programming Language :: Python :: 3.13
Classifier: Programming Language :: Python :: 3.14
Classifier: Programming Language :: Python :: 3 :: Only
Classifier: Topic :: Home Automation
Requires-Python: >=3.10
License-File: LICENSE
Requires-Dist: aiomqtt==2.4.0
Requires-Dist: pyserial-asyncio==0.6
Requires-Dist: easyconfig==0.4.2
Requires-Dist: pydantic==2.12.3
Requires-Dist: smllib==1.7
Requires-Dist: aiohttp==3.13.2
Dynamic: author
Dynamic: classifier
Dynamic: description
Dynamic: description-content-type
Dynamic: home-page
Dynamic: keywords
Dynamic: license-file
Dynamic: project-url
Dynamic: requires-dist
Dynamic: requires-python
Dynamic: summary
